{
    "errors": [
        "Unknown operation"
    ],
    "fails": [],
    "findings": [
        {
            "filename": "../retrospective-sc-analysis/data/bytecodes/eth/0x606e9758a39d2d7fa7e70bc68e6e7d9b02948962.hex",
            "name": "Not destructible (no self-destruct)"
        },
        {
            "filename": "../retrospective-sc-analysis/data/bytecodes/eth/0x606e9758a39d2d7fa7e70bc68e6e7d9b02948962.hex",
            "name": "Ether lock"
        }
    ],
    "infos": [],
    "parser": {
        "id": "maian",
        "mode": "runtime",
        "version": "2022/11/11"
    }
}
